MANIFEST.in
README.md
setup.cfg
setup.py
bin/gAperture
bin/gFind
bin/gMap
bin/gPipeline
gPhoton/CalUtils.py
gPhoton/CalibrationTools.py
gPhoton/FileUtils.py
gPhoton/MCUtils.py
gPhoton/PhotonPipe.py
gPhoton/__init__.py
gPhoton/curvetools.py
gPhoton/dbasetools.py
gPhoton/gAperture.py
gPhoton/gCalrun.py
gPhoton/gFind.py
gPhoton/gMap.py
gPhoton/gPipeline.py
gPhoton/gQuery.py
gPhoton/galextools.py
gPhoton/gnomonic.py
gPhoton/gphoton_args.py
gPhoton/gphoton_utils.py
gPhoton/imagetools.py
gPhoton/regtestutils.py
gPhoton.egg-info/PKG-INFO
gPhoton.egg-info/SOURCES.txt
gPhoton.egg-info/dependency_links.txt
gPhoton.egg-info/not-zip-safe
gPhoton.egg-info/requires.txt
gPhoton.egg-info/top_level.txt
gPhoton/cal/__init__.py
gPhoton/cal/__pycache__/__init__.cpython-36.pyc